{"book_list": [{"title": "\uc2e4\uc804\uc5d0\uc11c \ubc14\ub85c \uc4f0\ub294 Next.js", "price": "26,000\uc6d0", "author": "\ubbf8\uc178 \ub9ac\ubc14 ", "reldate": "2023-01-20", "pages": "332 \ucabd"}, {"title": "(NO.1 \uc601\uc0c1 \ud3b8\uc9d1 \uc720\ud29c\ubc84) \ube44\ub434\ud074\ub798\uc2a4\uc758 \uc720\ud29c\ube0c \uc601\uc0c1 \ud3b8\uc9d1 with \ud504\ub9ac\ubbf8\uc5b4 \ud504\ub85c", "price": "23,000\uc6d0", "author": "\ud558\uc9c0\uc6d0(\ube44\ub434\ud074\ub798\uc2a4) ", "reldate": "2023-01-18", "pages": "372 \ucabd"}, {"title": "\uc5c5\ubb34\uc5d0 \ubc14\ub85c \uc4f0\ub294 AWS \uc785\ubb38", "price": "27,000\uc6d0", "author": "\uae40\uc131\ubbfc ", "reldate": "2023-01-10", "pages": "360 \ucabd"}, {"title": "\ub098\ub3c4 \uc190\uae00\uc528 \ubc18\ub4ef\ud558\uac8c \uc798 \uc4f0\uba74 \uc18c\uc6d0\uc774 \uc5c6\uaca0\ub124", "price": "13,800\uc6d0", "author": "\uc720\ud55c\ube48(\ud39c\ud06c\ub798\ud504\ud2b8) ", "reldate": "2023-01-06", "pages": "160 \ucabd"}, {"title": "\uc131\uacf5\ud558\ub294 \uc720\ud29c\ube0c \ucc44\ub110\uc740 \ub530\ub85c \uc788\ub2e4", "price": "18,000\uc6d0", "author": "\uac15\ucc28\ubd84PD ", "reldate": "2023-01-06", "pages": "320 \ucabd"}, {"title": "\ud504\ub85c\ub355\ud2b8 \ub9e4\ub2c8\uc800\ub294 \ubb34\uc2a8 \uc77c\uc744 \ud558\uace0 \uc788\uc744\uae4c", "price": "20,000\uc6d0", "author": "\uac1c\uc810\ud734\uc5c5 , \ucd5c\ubbfc ", "reldate": "2023-01-06", "pages": "244 \ucabd"}, {"title": "IT CookBook, \ucef4\ud4e8\ud130 \ube44\uc804\uacfc \ub525\ub7ec\ub2dd", "price": "39,000\uc6d0", "author": "\uc624\uc77c\uc11d ", "reldate": "2023-01-05", "pages": "664 \ucabd"}, {"title": "[\uc5c9\ub6b1\uc18c\uc2ec \uc720\ub839 \ud0d0\uc815\ub2e8] 3. \ubb34\ub300 \ub4a4\uc758 \uc720\ub839", "price": "13,000\uc6d0", "author": "\ub3c4\ub9ac \ud790\ub808\uc2a4\ud0c0\ub4dc \ubc84\ud2c0\ub7ec , \uc624\ub85c\ub974 \ub2e4\ub9dd(\uadf8\ub9bc) ", "reldate": "2023-01-05", "pages": "132 \ucabd"}, {"title": "\uc720\ub7fd \ud48d\uacbd \uc218\ucc44\ud654 \uceec\ub7ec\ub9c1\ubd81", "price": "17,500\uc6d0", "author": "\uc815\uc9c4\ud638 ", "reldate": "2023-01-05", "pages": "148 \ucabd"}, {"title": "\ub7ec\ub2dd \ud0c0\uc785\uc2a4\ud06c\ub9bd\ud2b8", "price": "26,000\uc6d0", "author": "\uc870\uc2dc \uace8\ub4dc\ubc84\uadf8 ", "reldate": "2023-01-02", "pages": "372 \ucabd"}, {"title": "\ub9ac\ub354\uc2ed : \uc774\ub860\uacfc \uc2e4\uc81c (9\ud310)", "price": "36,000\uc6d0", "author": "Peter G. Northouse ", "reldate": "2023-01-02", "pages": "660 \ucabd"}, {"title": "\ud63c\uc790 \uacf5\ubd80\ud558\ub294 \ub370\uc774\ud130 \ubd84\uc11d with \ud30c\uc774\uc36c", "price": "26,000\uc6d0", "author": "\ubc15\ud574\uc120 ", "reldate": "2023-01-02", "pages": "496 \ucabd"}, {"title": "IT CookBook, JAVA \ub9c8\uc2a4\ud130", "price": "30,000\uc6d0", "author": "\uc1a1\ubbf8\uc601 ", "reldate": "2023-01-01", "pages": "732 \ucabd"}, {"title": "IT CookBook, \ub370\uc774\ud130 \uacfc\ud559\uc744 \uc704\ud55c \ud30c\uc774\uc36c \ud504\ub85c\uadf8\ub798\ubc0d(2\ud310)", "price": "30,000\uc6d0", "author": "\ucd5c\uc131\ucca0 ", "reldate": "2023-01-01", "pages": "540 \ucabd"}, {"title": "IT CookBook, \uc0dd\ud65c \uc18d \uc608\uc81c\ub85c \ubc30\uc6b0\ub294 \uc0dd\uc0dd \ub370\uc774\ud130 \ubd84\uc11d", "price": "23,000\uc6d0", "author": "\uc870\uc778\uc11d ", "reldate": "2023-01-01", "pages": "428 \ucabd"}, {"title": "IT CookBook, \ud30c\uc6cc\ud3ec\uc778\ud2b8 2019", "price": "20,000\uc6d0", "author": "\uae40\uc9c0\uc5f0 ", "reldate": "2023-01-01", "pages": "440 \ucabd"}, {"title": "\uba54\ud0c0\ubc84\uc2a4\ub85c \uad6c\ud604\ud558\ub294 \ub098\ub9cc\uc758 \uc138\uc0c1", "price": "23,000\uc6d0", "author": "\ud55c\uaddc\uc815 , \ucd5c\uc885\uc6d0 , \uac15\uc2e0\uc870 , \uc2ec\ubbfc\uc815 , \uc548\ud615\uc900 , \uc704\uc0c8\ub78c , \ucd5c\ub3d9\uc77c ", "reldate": "2023-01-01", "pages": "388 \ucabd"}, {"title": "\uad6d\uc81c\uacbd\uc601\ud559 : \ud658\uacbd\uacfc \uc6b4\uc601 (17\ud310)", "price": "41,000\uc6d0", "author": "John D. Daniels , Lee H. Radebaugh , Daniel P. Sullivan , Reid W. Click ", "reldate": "2022-12-30", "pages": "716 \ucabd"}, {"title": "\uc720\ub958\ud488 \uc774\uc57c\uae30", "price": "19,800\uc6d0", "author": "\ub85c\ubc84\ud2b8 \uc820\uc2a8 ", "reldate": "2022-12-30", "pages": "408 \ucabd"}, {"title": "\uc790\ubc14\uc2a4\ud06c\ub9bd\ud2b8\ub85c \ubc30\uc6b0\ub294 SICP", "price": "45,000\uc6d0", "author": "\ud574\ub7f4\ub4dc \uc5d0\uc774\ube14\uc2a8 , \uc81c\ub7f4\ub4dc \uc81c\uc774 \uc11c\uc2a4\uba3c , \ub9c8\ud2f4 \ud5e8\uc988 , \ud1a0\ube44\uc544\uc2a4 \ube0c\ub9ad\uc2a4\ud0c0\ub4dc , \uc904\ub9ac \uc11c\uc2a4\uba3c ", "reldate": "2022-12-30", "pages": "884 \ucabd"}]}